setup.py
pho_mos/__init__.py
pho_mos.egg-info/PKG-INFO
pho_mos.egg-info/SOURCES.txt
pho_mos.egg-info/dependency_links.txt
pho_mos.egg-info/top_level.txt
pho_mos/mosaic/__init__.py
pho_mos/mosaic/mosaic.py
pho_mos/mosaic/preprocessing.py
pho_mos/mosaic/shapes.py
pho_mos/mosaic/transforms.py
pho_mos/mosaic/util.py
pho_mos/util/__init__.py
pho_mos/util/file_hash.py
pho_mos/util/logs.py
pho_mos/util/parallel.py
pho_mos/util/translit.py