Metadata-Version: 1.2
Name: pho-mos
Version: 0.0.4
Summary: Photo mosaic
Home-page: https://github.com/botanhuligan/pho_mos
Author: Vitaliy Rakitin
Author-email: vitaliyrakitin@ya.ru
License: UNKNOWN
Platform: UNKNOWN
Classifier: Programming Language :: Python :: 3
Classifier: License :: OSI Approved :: MIT License
Classifier: Operating System :: OS Independent
Requires-Python: >=3.6
